assistants/__init__.py
assistants/assistants.py
openainode/__init__.py
openainode/openai_model.py
openainode/openai_node.py
Open_ChatGPT_Plugins-0.1.0.dist-info/LICENSE
Open_ChatGPT_Plugins-0.1.0.dist-info/METADATA
Open_ChatGPT_Plugins-0.1.0.dist-info/WHEEL
Open_ChatGPT_Plugins-0.1.0.dist-info/top_level.txt
Open_ChatGPT_Plugins-0.1.0.dist-info/RECORD
